[
  {
    "amount": 500,
    "description": "Grocery on Blinkit",
    "category": "Grocery",
    "type": "expense",
    "date": "2025-11-27T05:24:26.088Z",
    "id": "258004fd-b34c-4a88-bae1-c4affc2a2086",
    "userId": "geetp9903"
  },
  {
    "amount": 25000,
    "description": "Recent",
    "category": "Monthly",
    "type": "income",
    "date": "2025-11-27T05:25:08.965Z",
    "id": "c300469e-6221-483c-9fd8-44cf215e37e5",
    "userId": "geetp9903"
  },
  {
    "amount": 496,
    "description": "Blinkit",
    "category": "Grocery",
    "type": "expense",
    "date": "2025-11-27T07:12:37.834Z",
    "id": "4cd0b907-987e-43fe-8a45-8e042f1154f1",
    "userId": "geetp9903"
  }
]